[
  {
    "id": "bbf4169a2b6cbe2ecbde3be8e27c7fe8",
    "source_archive": "Manar al-Athar",
    "source_url": "https://www.manar-al-athar.ox.ac.uk/filestore/1/0/9/4/0/7_008eeffa09e7bde/109407pre_5f072b4373a196a.jpg?v=2019-11-20+10%3A36%3A04",
    "title": "Manar al-Athar Archaeological Image",
    "description": "",
    "date_created": null,
    "date_range_start": null,
    "date_range_end": null,
    "date_uncertainty": null,
    "subject": [],
    "keywords": [],
    "data_type": "image",
    "mime_type": "",
    "file_format": "",
    "dimensions": null,
    "file_size": null,
    "resolution": null,
    "location": null,
    "coverage_spatial": [],
    "creator": [],
    "contributor": [],
    "publisher": null,
    "rights": null,
    "license": null,
    "access_restrictions": null,
    "language": [],
    "script": null,
    "is_part_of": null,
    "related_items": [],
    "download_url": "https://www.manar-al-athar.ox.ac.uk/filestore/1/0/9/4/0/7_008eeffa09e7bde/109407pre_5f072b4373a196a.jpg?v=2019-11-20+10%3A36%3A04",
    "thumbnail_url": "https://www.manar-al-athar.ox.ac.uk/filestore/1/0/9/4/0/7_008eeffa09e7bde/109407pre_5f072b4373a196a.jpg?v=2019-11-20+10%3A36%3A04",
    "iiif_manifest": null,
    "harvested_date": "2025-06-11T16:16:28.929114",
    "processing_notes": [],
    "confidence_score": 1.0,
    "raw_metadata": {}
  },
  {
    "id": "e37d0353d2a1e3c988b608094df6fbb1",
    "source_archive": "Manar al-Athar",
    "source_url": "https://www.manar-al-athar.ox.ac.uk/filestore/1/0/9/4/0/6_80cbab450fee765/109406pre_e36a58d3d90d05a.jpg?v=2019-11-20+10%3A36%3A03",
    "title": "Manar al-Athar Archaeological Image",
    "description": "",
    "date_created": null,
    "date_range_start": null,
    "date_range_end": null,
    "date_uncertainty": null,
    "subject": [],
    "keywords": [],
    "data_type": "image",
    "mime_type": "",
    "file_format": "",
    "dimensions": null,
    "file_size": null,
    "resolution": null,
    "location": null,
    "coverage_spatial": [],
    "creator": [],
    "contributor": [],
    "publisher": null,
    "rights": null,
    "license": null,
    "access_restrictions": null,
    "language": [],
    "script": null,
    "is_part_of": null,
    "related_items": [],
    "download_url": "https://www.manar-al-athar.ox.ac.uk/filestore/1/0/9/4/0/6_80cbab450fee765/109406pre_e36a58d3d90d05a.jpg?v=2019-11-20+10%3A36%3A03",
    "thumbnail_url": "https://www.manar-al-athar.ox.ac.uk/filestore/1/0/9/4/0/6_80cbab450fee765/109406pre_e36a58d3d90d05a.jpg?v=2019-11-20+10%3A36%3A03",
    "iiif_manifest": null,
    "harvested_date": "2025-06-11T16:16:28.929164",
    "processing_notes": [],
    "confidence_score": 1.0,
    "raw_metadata": {}
  },
  {
    "id": "48bba1ddae1beacf6b2c757fbdc68563",
    "source_archive": "Manar al-Athar",
    "source_url": "https://www.manar-al-athar.ox.ac.uk/filestore/1/0/9/4/0/5_d92a7ed7b15895b/109405pre_d5299faa28aba12.jpg?v=2019-11-20+10%3A36%3A01",
    "title": "Manar al-Athar Archaeological Image",
    "description": "",
    "date_created": null,
    "date_range_start": null,
    "date_range_end": null,
    "date_uncertainty": null,
    "subject": [],
    "keywords": [],
    "data_type": "image",
    "mime_type": "",
    "file_format": "",
    "dimensions": null,
    "file_size": null,
    "resolution": null,
    "location": null,
    "coverage_spatial": [],
    "creator": [],
    "contributor": [],
    "publisher": null,
    "rights": null,
    "license": null,
    "access_restrictions": null,
    "language": [],
    "script": null,
    "is_part_of": null,
    "related_items": [],
    "download_url": "https://www.manar-al-athar.ox.ac.uk/filestore/1/0/9/4/0/5_d92a7ed7b15895b/109405pre_d5299faa28aba12.jpg?v=2019-11-20+10%3A36%3A01",
    "thumbnail_url": "https://www.manar-al-athar.ox.ac.uk/filestore/1/0/9/4/0/5_d92a7ed7b15895b/109405pre_d5299faa28aba12.jpg?v=2019-11-20+10%3A36%3A01",
    "iiif_manifest": null,
    "harvested_date": "2025-06-11T16:16:28.929169",
    "processing_notes": [],
    "confidence_score": 1.0,
    "raw_metadata": {}
  },
  {
    "id": "7490fd5a4f576510fdc28bd8b2ec4d60",
    "source_archive": "Manar al-Athar",
    "source_url": "https://www.manar-al-athar.ox.ac.uk/filestore/1/0/9/4/0/4_7ca94ee762dbfee/109404pre_861fe459880cedd.jpg?v=2019-11-20+10%3A36%3A00",
    "title": "Manar al-Athar Archaeological Image",
    "description": "",
    "date_created": null,
    "date_range_start": null,
    "date_range_end": null,
    "date_uncertainty": null,
    "subject": [],
    "keywords": [],
    "data_type": "image",
    "mime_type": "",
    "file_format": "",
    "dimensions": null,
    "file_size": null,
    "resolution": null,
    "location": null,
    "coverage_spatial": [],
    "creator": [],
    "contributor": [],
    "publisher": null,
    "rights": null,
    "license": null,
    "access_restrictions": null,
    "language": [],
    "script": null,
    "is_part_of": null,
    "related_items": [],
    "download_url": "https://www.manar-al-athar.ox.ac.uk/filestore/1/0/9/4/0/4_7ca94ee762dbfee/109404pre_861fe459880cedd.jpg?v=2019-11-20+10%3A36%3A00",
    "thumbnail_url": "https://www.manar-al-athar.ox.ac.uk/filestore/1/0/9/4/0/4_7ca94ee762dbfee/109404pre_861fe459880cedd.jpg?v=2019-11-20+10%3A36%3A00",
    "iiif_manifest": null,
    "harvested_date": "2025-06-11T16:16:28.929174",
    "processing_notes": [],
    "confidence_score": 1.0,
    "raw_metadata": {}
  },
  {
    "id": "35227547c29e0a3cea9d7f2c7f0b8555",
    "source_archive": "Manar al-Athar",
    "source_url": "https://www.manar-al-athar.ox.ac.uk/filestore/1/0/9/4/0/3_2048ac81442561d/109403pre_197538871c9a9bf.jpg?v=2019-11-20+10%3A35%3A58",
    "title": "Manar al-Athar Archaeological Image",
    "description": "",
    "date_created": null,
    "date_range_start": null,
    "date_range_end": null,
    "date_uncertainty": null,
    "subject": [],
    "keywords": [],
    "data_type": "image",
    "mime_type": "",
    "file_format": "",
    "dimensions": null,
    "file_size": null,
    "resolution": null,
    "location": null,
    "coverage_spatial": [],
    "creator": [],
    "contributor": [],
    "publisher": null,
    "rights": null,
    "license": null,
    "access_restrictions": null,
    "language": [],
    "script": null,
    "is_part_of": null,
    "related_items": [],
    "download_url": "https://www.manar-al-athar.ox.ac.uk/filestore/1/0/9/4/0/3_2048ac81442561d/109403pre_197538871c9a9bf.jpg?v=2019-11-20+10%3A35%3A58",
    "thumbnail_url": "https://www.manar-al-athar.ox.ac.uk/filestore/1/0/9/4/0/3_2048ac81442561d/109403pre_197538871c9a9bf.jpg?v=2019-11-20+10%3A35%3A58",
    "iiif_manifest": null,
    "harvested_date": "2025-06-11T16:16:28.929178",
    "processing_notes": [],
    "confidence_score": 1.0,
    "raw_metadata": {}
  },
  {
    "id": "40c6b6801964e7a286f24f13659a46d5",
    "source_archive": "Manar al-Athar",
    "source_url": "https://www.manar-al-athar.ox.ac.uk/filestore/1/0/9/4/0/2_27d4c8b186d45dd/109402pre_cb34e5be35dd06c.jpg?v=2019-11-20+10%3A35%3A56",
    "title": "Manar al-Athar Archaeological Image",
    "description": "",
    "date_created": null,
    "date_range_start": null,
    "date_range_end": null,
    "date_uncertainty": null,
    "subject": [],
    "keywords": [],
    "data_type": "image",
    "mime_type": "",
    "file_format": "",
    "dimensions": null,
    "file_size": null,
    "resolution": null,
    "location": null,
    "coverage_spatial": [],
    "creator": [],
    "contributor": [],
    "publisher": null,
    "rights": null,
    "license": null,
    "access_restrictions": null,
    "language": [],
    "script": null,
    "is_part_of": null,
    "related_items": [],
    "download_url": "https://www.manar-al-athar.ox.ac.uk/filestore/1/0/9/4/0/2_27d4c8b186d45dd/109402pre_cb34e5be35dd06c.jpg?v=2019-11-20+10%3A35%3A56",
    "thumbnail_url": "https://www.manar-al-athar.ox.ac.uk/filestore/1/0/9/4/0/2_27d4c8b186d45dd/109402pre_cb34e5be35dd06c.jpg?v=2019-11-20+10%3A35%3A56",
    "iiif_manifest": null,
    "harvested_date": "2025-06-11T16:16:28.929182",
    "processing_notes": [],
    "confidence_score": 1.0,
    "raw_metadata": {}
  },
  {
    "id": "053a524b40eb31d66da6bc34c3464017",
    "source_archive": "Manar al-Athar",
    "source_url": "https://www.manar-al-athar.ox.ac.uk/filestore/1/0/9/4/0/1_defd754e98c65ea/109401pre_aae0c211235d255.jpg?v=2019-11-20+10%3A35%3A54",
    "title": "Manar al-Athar Archaeological Image",
    "description": "",
    "date_created": null,
    "date_range_start": null,
    "date_range_end": null,
    "date_uncertainty": null,
    "subject": [],
    "keywords": [],
    "data_type": "image",
    "mime_type": "",
    "file_format": "",
    "dimensions": null,
    "file_size": null,
    "resolution": null,
    "location": null,
    "coverage_spatial": [],
    "creator": [],
    "contributor": [],
    "publisher": null,
    "rights": null,
    "license": null,
    "access_restrictions": null,
    "language": [],
    "script": null,
    "is_part_of": null,
    "related_items": [],
    "download_url": "https://www.manar-al-athar.ox.ac.uk/filestore/1/0/9/4/0/1_defd754e98c65ea/109401pre_aae0c211235d255.jpg?v=2019-11-20+10%3A35%3A54",
    "thumbnail_url": "https://www.manar-al-athar.ox.ac.uk/filestore/1/0/9/4/0/1_defd754e98c65ea/109401pre_aae0c211235d255.jpg?v=2019-11-20+10%3A35%3A54",
    "iiif_manifest": null,
    "harvested_date": "2025-06-11T16:16:28.929188",
    "processing_notes": [],
    "confidence_score": 1.0,
    "raw_metadata": {}
  },
  {
    "id": "60b79bbfec6c34f9d3e27564d3c31540",
    "source_archive": "Manar al-Athar",
    "source_url": "https://www.manar-al-athar.ox.ac.uk/filestore/1/0/9/4/0/0_b8fef620d258b45/109400pre_6faba49fb9283c4.jpg?v=2019-11-20+10%3A35%3A52",
    "title": "Manar al-Athar Archaeological Image",
    "description": "",
    "date_created": null,
    "date_range_start": null,
    "date_range_end": null,
    "date_uncertainty": null,
    "subject": [],
    "keywords": [],
    "data_type": "image",
    "mime_type": "",
    "file_format": "",
    "dimensions": null,
    "file_size": null,
    "resolution": null,
    "location": null,
    "coverage_spatial": [],
    "creator": [],
    "contributor": [],
    "publisher": null,
    "rights": null,
    "license": null,
    "access_restrictions": null,
    "language": [],
    "script": null,
    "is_part_of": null,
    "related_items": [],
    "download_url": "https://www.manar-al-athar.ox.ac.uk/filestore/1/0/9/4/0/0_b8fef620d258b45/109400pre_6faba49fb9283c4.jpg?v=2019-11-20+10%3A35%3A52",
    "thumbnail_url": "https://www.manar-al-athar.ox.ac.uk/filestore/1/0/9/4/0/0_b8fef620d258b45/109400pre_6faba49fb9283c4.jpg?v=2019-11-20+10%3A35%3A52",
    "iiif_manifest": null,
    "harvested_date": "2025-06-11T16:16:28.929196",
    "processing_notes": [],
    "confidence_score": 1.0,
    "raw_metadata": {}
  },
  {
    "id": "67190a4ed5be2b594aa2b0709b56bc60",
    "source_archive": "Manar al-Athar",
    "source_url": "https://www.manar-al-athar.ox.ac.uk/filestore/1/0/9/3/9/9_be71063ab8f3e99/109399pre_13dbac3204cda90.jpg?v=2019-11-20+10%3A35%3A50",
    "title": "Manar al-Athar Archaeological Image",
    "description": "",
    "date_created": null,
    "date_range_start": null,
    "date_range_end": null,
    "date_uncertainty": null,
    "subject": [],
    "keywords": [],
    "data_type": "image",
    "mime_type": "",
    "file_format": "",
    "dimensions": null,
    "file_size": null,
    "resolution": null,
    "location": null,
    "coverage_spatial": [],
    "creator": [],
    "contributor": [],
    "publisher": null,
    "rights": null,
    "license": null,
    "access_restrictions": null,
    "language": [],
    "script": null,
    "is_part_of": null,
    "related_items": [],
    "download_url": "https://www.manar-al-athar.ox.ac.uk/filestore/1/0/9/3/9/9_be71063ab8f3e99/109399pre_13dbac3204cda90.jpg?v=2019-11-20+10%3A35%3A50",
    "thumbnail_url": "https://www.manar-al-athar.ox.ac.uk/filestore/1/0/9/3/9/9_be71063ab8f3e99/109399pre_13dbac3204cda90.jpg?v=2019-11-20+10%3A35%3A50",
    "iiif_manifest": null,
    "harvested_date": "2025-06-11T16:16:28.929201",
    "processing_notes": [],
    "confidence_score": 1.0,
    "raw_metadata": {}
  },
  {
    "id": "064b4a1dc1839a50f226bcac9e1242c6",
    "source_archive": "Manar al-Athar",
    "source_url": "https://www.manar-al-athar.ox.ac.uk/filestore/1/0/9/3/9/8_dccd67b0db33587/109398pre_e24c51764b5d53f.jpg?v=2019-11-20+10%3A35%3A48",
    "title": "Manar al-Athar Archaeological Image",
    "description": "",
    "date_created": null,
    "date_range_start": null,
    "date_range_end": null,
    "date_uncertainty": null,
    "subject": [],
    "keywords": [],
    "data_type": "image",
    "mime_type": "",
    "file_format": "",
    "dimensions": null,
    "file_size": null,
    "resolution": null,
    "location": null,
    "coverage_spatial": [],
    "creator": [],
    "contributor": [],
    "publisher": null,
    "rights": null,
    "license": null,
    "access_restrictions": null,
    "language": [],
    "script": null,
    "is_part_of": null,
    "related_items": [],
    "download_url": "https://www.manar-al-athar.ox.ac.uk/filestore/1/0/9/3/9/8_dccd67b0db33587/109398pre_e24c51764b5d53f.jpg?v=2019-11-20+10%3A35%3A48",
    "thumbnail_url": "https://www.manar-al-athar.ox.ac.uk/filestore/1/0/9/3/9/8_dccd67b0db33587/109398pre_e24c51764b5d53f.jpg?v=2019-11-20+10%3A35%3A48",
    "iiif_manifest": null,
    "harvested_date": "2025-06-11T16:16:28.929204",
    "processing_notes": [],
    "confidence_score": 1.0,
    "raw_metadata": {}
  }
]